{
	"name": "rails-stations",
	"dockerComposeFile": "../docker-compose.yml",
	"workspaceFolder": "/app",
	"service": "web",
	"customizations": {
		"vscode": {
			"settings": {
				"editor.formatOnSave": true
			},
			"extensions": [
				"eamodio.gitlens",
				"cschleiden.vscode-github-actions",
				"github.vscode-pull-request-github",
				"hashicorp.terraform",
				"ms-azuretools.vscode-docker",
				"ms-vsliveshare.vsliveshare",
				"shd101wyy.markdown-preview-enhanced",
				"irongeek.vscode-env",
				"rogalmic.bash-debug",
				"hediet.vscode-drawio",
				"kaiwood.endwise",
				"oderwat.indent-rainbow",
				"mosapride.zenkaku",
				"aaron-bond.better-comments",
				"TechTrain.railway-vscode",
				"aliariff.vscode-erb-beautify",
				"misogi.ruby-rubocop",
				"castwide.solargraph",
				"rebornix.Ruby"
			]
		}
	},
	"postCreateCommand": "bash .devcontainer/postCreateCommand.sh"
}
